{
    "keep": {
        "days": true,
        "amount": 1
    },
    "auditLog": "C:\\Users\\Asif Abdul Owadud\\Desktop\\everything_asif\\everything_office\\everything_sparktech\\kappes_backend\\winston\\error\\.9693c46064b47537d25a75149f68832ed4e6ba76-audit.json",
    "files": [
        {
            "date": 1751100591843,
            "name": "C:\\Users\\Asif Abdul Owadud\\Desktop\\everything_asif\\everything_office\\everything_sparktech\\kappes_backend\\winston\\error\\28-06-2025-14-error.log",
            "hash": "a9af64a86a5a1b2b27caca54b6ca0d4a290a91ed70889bb7323a46486213b4e5"
        },
        {
            "date": 1751162970148,
            "name": "C:\\Users\\Asif Abdul Owadud\\Desktop\\everything_asif\\everything_office\\everything_sparktech\\kappes_backend\\winston\\error\\29-06-2025-08-error.log",
            "hash": "fc94efbfab1cd90b1160a7a0e29c4cf4b7dfb4758916641700225ebf3a061e58"
        },
        {
            "date": 1751166199299,
            "name": "C:\\Users\\Asif Abdul Owadud\\Desktop\\everything_asif\\everything_office\\everything_sparktech\\kappes_backend\\winston\\error\\29-06-2025-09-error.log",
            "hash": "e471be2e474da84521406c5fea192419133649c04f8c5b67c127ba85a42c700e"
        },
        {
            "date": 1751169641145,
            "name": "C:\\Users\\Asif Abdul Owadud\\Desktop\\everything_asif\\everything_office\\everything_sparktech\\kappes_backend\\winston\\error\\29-06-2025-10-error.log",
            "hash": "5af228cfe565549d615c5db44bf321277e831f042e0d46593c1081a2266d3625"
        },
        {
            "date": 1751173203887,
            "name": "C:\\Users\\Asif Abdul Owadud\\Desktop\\everything_asif\\everything_office\\everything_sparktech\\kappes_backend\\winston\\error\\29-06-2025-11-error.log",
            "hash": "6eba073d6a930b3975c2974ca58a369dfb75221b48300945ae85412f2030cc8b"
        },
        {
            "date": 1751176945281,
            "name": "C:\\Users\\Asif Abdul Owadud\\Desktop\\everything_asif\\everything_office\\everything_sparktech\\kappes_backend\\winston\\error\\29-06-2025-12-error.log",
            "hash": "e37dce9bac71f94b1535a3ebd72fc161eb4a45e6ed0cf060abf112a99d796cb8"
        },
        {
            "date": 1751180468894,
            "name": "C:\\Users\\Asif Abdul Owadud\\Desktop\\everything_asif\\everything_office\\everything_sparktech\\kappes_backend\\winston\\error\\29-06-2025-13-error.log",
            "hash": "e94082d5fa4fcef699c86042bfc54d6d18e83d877fd26737a1adf8e1d958fe97"
        }
    ],
    "hashType": "sha256"
}